commons_lang/__init__.py
commons_lang/concurrent/__init__.py
commons_lang/concurrent/atomic_bool.py
commons_lang/concurrent/count_down_latch.py
commons_lang/event/__init__.py
commons_lang/exception/__init__.py
commons_lang/exception/exception_utils.py
commons_lang/function/__init__.py
commons_lang/function/decorator.py
commons_lang/function/function_utils.py
commons_lang/logging/__init__.py
commons_lang/logging/logger.py
commons_lang/object/__init__.py
commons_lang/object/decorator.py
commons_lang/object_utils.py
commons_lang/text/__init__.py
commons_lang/text/string_utils.py
commons_lang/time/__init__.py
commons_lang/utils/__init__.py
commons_lang-0.2.13.dist-info/METADATA
commons_lang-0.2.13.dist-info/WHEEL
commons_lang-0.2.13.dist-info/RECORD
