Metadata-Version: 2.3
Name: commons-lang
Version: 0.2.13
Summary: 
Author: hzr
Author-email: 198436259@qq.com
Requires-Python: >=3.10,<4.0
Classifier: Programming Language :: Python :: 3
Classifier: Programming Language :: Python :: 3.10
Classifier: Programming Language :: Python :: 3.11
Classifier: Programming Language :: Python :: 3.12
Classifier: Programming Language :: Python :: 3.13
Requires-Dist: loguru (>=0.7.3,<0.8.0)
Requires-Dist: poetry-core (>=2.0.0,<3.0.0)
